[
    {
        "key": "dbln",
        "value": "%7B%2261570107476269%22%3A%22xtjy9Vcn%22%2C%2261579221186551%22%3A%22QNWTeseQ%22%2C%2261578903987238%22%3A%22vPzBAuru%22%7D",
        "domain": "facebook.com",
        "path": "/login/device-based/",
        "hostOnly": false,
        "creation": "2025-08-20T13:44:12.848Z",
        "lastAccessed": "2025-08-20T13:44:12.848Z"
    },
    {
        "key": "datr",
        "value": "lzyfaN8KxXhFG34BaMRtX_XQ",
        "domain": "facebook.com",
        "path": "/",
        "hostOnly": false,
        "creation": "2025-08-20T13:44:12.848Z",
        "lastAccessed": "2025-08-20T13:44:12.848Z"
    },
    {
        "key": "sb",
        "value": "lzyfaFjC3_358JwyMUymbhXC",
        "domain": "facebook.com",
        "path": "/",
        "hostOnly": false,
        "creation": "2025-08-20T13:44:12.848Z",
        "lastAccessed": "2025-08-20T13:44:12.848Z"
    },
    {
        "key": "ps_l",
        "value": "1",
        "domain": "facebook.com",
        "path": "/",
        "hostOnly": false,
        "creation": "2025-08-20T13:44:12.848Z",
        "lastAccessed": "2025-08-20T13:44:12.848Z"
    },
    {
        "key": "ps_n",
        "value": "1",
        "domain": "facebook.com",
        "path": "/",
        "hostOnly": false,
        "creation": "2025-08-20T13:44:12.848Z",
        "lastAccessed": "2025-08-20T13:44:12.848Z"
    },
    {
        "key": "locale",
        "value": "en_GB",
        "domain": "facebook.com",
        "path": "/",
        "hostOnly": false,
        "creation": "2025-08-20T13:44:12.848Z",
        "lastAccessed": "2025-08-20T13:44:12.848Z"
    },
    {
        "key": "vpd",
        "value": "v1%3B680x360x3",
        "domain": "facebook.com",
        "path": "/",
        "hostOnly": false,
        "creation": "2025-08-20T13:44:12.848Z",
        "lastAccessed": "2025-08-20T13:44:12.848Z"
    },
    {
        "key": "m_pixel_ratio",
        "value": "3",
        "domain": "facebook.com",
        "path": "/",
        "hostOnly": false,
        "creation": "2025-08-20T13:44:12.848Z",
        "lastAccessed": "2025-08-20T13:44:12.848Z"
    },
    {
        "key": "wd",
        "value": "360x820",
        "domain": "facebook.com",
        "path": "/",
        "hostOnly": false,
        "creation": "2025-08-20T13:44:12.848Z",
        "lastAccessed": "2025-08-20T13:44:12.848Z"
    },
    {
        "key": "c_user",
        "value": "61578903987238",
        "domain": "facebook.com",
        "path": "/",
        "hostOnly": false,
        "creation": "2025-08-20T13:44:12.848Z",
        "lastAccessed": "2025-08-20T13:44:12.848Z"
    },
    {
        "key": "xs",
        "value": "37%3Au5_xdyhoUC9qaw%3A2%3A1755697413%3A-1%3A-1",
        "domain": "facebook.com",
        "path": "/",
        "hostOnly": false,
        "creation": "2025-08-20T13:44:12.848Z",
        "lastAccessed": "2025-08-20T13:44:12.848Z"
    },
    {
        "key": "fr",
        "value": "0ilDWYoYoS2Xb02e2.AWdm1pWVilWJCtThpEV8MzrD2ULgyl2zCQzHGBYlvBHrAySTXmQ.BonzyX..AAA.0.0.BopdEN.AWerUQ_KP-7pMf7XAxjXcYeo42w",
        "domain": "facebook.com",
        "path": "/",
        "hostOnly": false,
        "creation": "2025-08-20T13:44:12.848Z",
        "lastAccessed": "2025-08-20T13:44:12.848Z"
    },
    {
        "key": "pas",
        "value": "61570107476269%3AW9OjoTqmme%2C61579221186551%3A1AOfarps7N%2C61578903987238%3AFNV90PZVQR",
        "domain": "facebook.com",
        "path": "/",
        "hostOnly": false,
        "creation": "2025-08-20T13:44:12.848Z",
        "lastAccessed": "2025-08-20T13:44:12.848Z"
    },
    {
        "key": "fbl_st",
        "value": "101239836%3BT%3A29261623",
        "domain": "facebook.com",
        "path": "/",
        "hostOnly": false,
        "creation": "2025-08-20T13:44:12.848Z",
        "lastAccessed": "2025-08-20T13:44:12.848Z"
    },
    {
        "key": "wl_cbv",
        "value": "v2%3Bclient_version%3A2898%3Btimestamp%3A1755697421",
        "domain": "facebook.com",
        "path": "/",
        "hostOnly": false,
        "creation": "2025-08-20T13:44:12.848Z",
        "lastAccessed": "2025-08-20T13:44:12.848Z"
    }
]
